LICENSE
baby_shap/__init__.py
baby_shap/_explanation.py
baby_shap/explainers/__init__.py
baby_shap/explainers/_explainer.py
baby_shap/explainers/_kernel.py
baby_shap/explainers/_linear.py
baby_shap/links.py
baby_shap/maskers/__init__.py
baby_shap/maskers/_masker.py
baby_shap/maskers/_tabular.py
baby_shap/plots/__init__.py
baby_shap/plots/_beeswarm.py
baby_shap/plots/_force.py
baby_shap/plots/_force_matplotlib.py
baby_shap/plots/_labels.py
baby_shap/plots/_summary.py
baby_shap/plots/_utils.py
baby_shap/plots/colors/__init__.py
baby_shap/plots/colors/_colorconv.py
baby_shap/plots/colors/_colors.py
baby_shap/plots/resources/bundle.js
baby_shap/plots/resources/logoSmallGray.png
baby_shap/utils/__init__.py
baby_shap/utils/_clustering.py
baby_shap/utils/_exceptions.py
baby_shap/utils/_general.py
baby_shap/utils/_legacy.py
baby_shap/utils/_show_progress.py
baby_shap-0.0.6.dist-info/LICENSE
baby_shap-0.0.6.dist-info/WHEEL
baby_shap-0.0.6.dist-info/METADATA
baby_shap-0.0.6.dist-info/RECORD
