Metadata-Version: 2.1
Name: baby-shap
Version: 0.0.6
Summary: A stripped and opiniated version of Scott Lundberg's SHAP (SHapley Additive exPlanations)
License: MIT
Keywords: shap
Author: Thom Hopmans
Requires-Python: >=3.10
Classifier: License :: OSI Approved :: MIT License
Classifier: Programming Language :: Python :: 3
Classifier: Programming Language :: Python :: 3.10
Classifier: Programming Language :: Python :: 3.11
Requires-Dist: ipython (>=8.0.0)
Requires-Dist: matplotlib (>=3.6.0)
Requires-Dist: numpy (>=1.19.0)
Requires-Dist: pandas (>=1.1.0)
Requires-Dist: scikit-learn (>=1.0.0)
Requires-Dist: slicer (>=0.0.7)
Requires-Dist: tqdm (>=4.64.1)
